Workbook
Name Comm: 'Emp Commission'!$D$2
Name MonthlyGoal: 'IF Function'!$I$2

Sheet Emp Commission
C2: Commission | D2: 0.04
A4: Sales Rep | B4: Region | C4: Monthly Sales | D4: Earned
A5: Alex | B5: West | C5: 42000 | D5: =C5*Comm -> 1680
A6: Morgan | B6: East | C6: 36000 | D6: =C6*Comm -> 1440
A7: Jamie | B7: Central | C7: 51000 | D7: =C7*Comm -> 2040
A8: Taylor | B8: West | C8: 27000 | D8: =C8*Comm -> 1080
A9: Jordan | B9: East | C9: 61000 | D9: =C9*Comm -> 2440

Sheet IF Function
A2: Sales Figures - December 2026 | H2: Monthly Goal: | I2: 34000
A4: Sales Person | B4: Week 1 | C4: Week 2 | D4: Week 3 | E4: Week 4 | F4: Totals | H4: Was Goal Met? | I4: Bonus Status
A5: H. James | B5: 9550 | C5: 9230 | D5: 8500 | E5: 8965 | F5: =SUM(B5:E5) -> 36245 | H5: =IF(F5>=MonthlyGoal,"YES","NO") -> YES | I5: =IF(AND(H5="YES",MIN(B5:E5)>=8000),"Yes Bonus", "No Bonus") -> Yes Bonus
A6: K. Dunn | B6: 5975 | C6: 6900 | D6: 8500 | E6: 10100 | F6: =SUM(B6:E6) -> 31475 | H6: =IF(F6>=MonthlyGoal,"YES","NO") -> NO | I6: =IF(AND(H6="YES",MIN(B6:E6)>=8000),"Yes Bonus", "No Bonus") -> No Bonus
A7: L. Carrie | B7: 7425 | C7: 8580 | D7: 9910 | E7: 7512 | F7: =SUM(B7:E7) -> 33427 | H7: =IF(F7>=MonthlyGoal,"YES","NO") -> NO | I7: =IF(AND(H7="YES",MIN(B7:E7)>=8000),"Yes Bonus", "No Bonus") -> No Bonus
A8: R. Smith | B8: 9560 | C8: 10150 | D8: 10200 | E8: 9795 | F8: =SUM(B8:E8) -> 39705 | H8: =IF(F8>=MonthlyGoal,"YES","NO") -> YES | I8: =IF(AND(H8="YES",MIN(B8:E8)>=8000),"Yes Bonus", "No Bonus") -> Yes Bonus
A9: D. O'Brian | B9: 7892 | C9: 7695 | D9: 9520 | E9: 10252 | F9: =SUM(B9:E9) -> 35359 | H9: =IF(F9>=MonthlyGoal,"YES","NO") -> YES | I9: =IF(AND(H9="YES",MIN(B9:E9)>=8000),"Yes Bonus", "No Bonus") -> No Bonus
A10: Weekly Total
A12: Current number of sales people who haved reached their goal: | F12: =COUNTIF(H5:H9,"YES") -> 3

Sheet SUMIF Function
A2: Month | B2: Store # | C2: SKU | D2: Sales | E2: Units | G2: Store # | H2: Month | I2: Total Units | J2: Total Sales
A3: JAN | B3: 1000 | C3: E0028M | D3: =E3*28 -> 9660 | E3: 345 | G3: 1000 | H3: Jan | I3: =SUMIF(B3:B272,G3,E3:E272) -> 16871 | J3: =SUMIFS(D3:D272,B3:B272,G3,A3:A272,H3) -> 155904
A4: JAN | B4: 1050 | C4: E0028M | D4: =E4*28 -> 5936 | E4: 212 | G4: SKU # | I4: Total Units | J4: Total Sales
A5: JAN | B5: 2000 | C5: E0028M | D5: =E5*28 -> 10136 | E5: 362 | G5: E0032M | H5: Jan | I5: =SUMIF(C3:C272,G5,E3:E272) -> 7357 | J5: =SUMIFS(D3:D272,C3:C272,G5,A3:A272,H5) -> 59864
A6: JAN | B6: 2050 | C6: E0028M | D6: =E6*28 -> 3388 | E6: 121
A7: JAN | B7: 3000 | C7: E0028M | D7: =E7*28 -> 14056 | E7: 502
A8: JAN | B8: 3050 | C8: E0028M | D8: =E8*28 -> 10136 | E8: 362
A9: JAN | B9: 1000 | C9: E0030M | D9: =E9*28 -> 14588 | E9: 521
A10: JAN | B10: 1050 | C10: E0030M | D10: =E10*28 -> 6552 | E10: 234
A11: JAN | B11: 2000 | C11: E0030M | D11: =E11*28 -> 11788 | E11: 421
A12: JAN | B12: 2050 | C12: E0030M | D12: =E12*28 -> 9072 | E12: 324
A13: JAN | B13: 3000 | C13: E0030M | D13: =E13*28 -> 3388 | E13: 121
A14: JAN | B14: 3050 | C14: E0030M | D14: =E14*28 -> 15176 | E14: 542
A15: JAN | B15: 1000 | C15: E0032M | D15: =E15*28 -> 5964 | E15: 213
A16: JAN | B16: 1050 | C16: E0032M | D16: =E16*28 -> 6748 | E16: 241
A17: JAN | B17: 2000 | C17: E0032M | D17: =E17*28 -> 11508 | E17: 411
... A272: MAR | B272: 3050 | C272: C0036M | D272: =E272*28 -> 11256 | E272: 402

Sheet VLOOKUP Function
B2: Emp ID | C2: First Name | D2: Last Name | E2: Dept | F2: Pay Rate
B3: 1054 | C3: =IFERROR(VLOOKUP(B3,'Master Emp List'!$A$2:$I$38,3,FALSE),"No EMP ID Found") -> Howard
B4: 1056 | C4: =IFERROR(VLOOKUP(B4,'Master Emp List'!$A$2:$I$38,3,FALSE),"No EMP ID Found") -> Joe
B5: 1067 | C5: =IFERROR(VLOOKUP(B5,'Master Emp List'!$A$2:$I$38,3,FALSE),"No EMP ID Found") -> Gail
B6: 1075 | C6: =IFERROR(VLOOKUP(B6,'Master Emp List'!$A$2:$I$38,3,FALSE),"No EMP ID Found") -> Sheryl
B7: 1078 | C7: =IFERROR(VLOOKUP(B7,'Master Emp List'!$A$2:$I$38,3,FALSE),"No EMP ID Found") -> Kendrick
B8: 1152 | C8: =IFERROR(VLOOKUP(B8,'Master Emp List'!$A$2:$I$38,3,FALSE),"No EMP ID Found") -> Mark
B9: 1196 | C9: =IFERROR(VLOOKUP(B9,'Master Emp List'!$A$2:$I$38,3,FALSE),"No EMP ID Found") -> Katie
B10: 1284 | C10: =IFERROR(VLOOKUP(B10,'Master Emp List'!$A$2:$I$38,3,FALSE),"No EMP ID Found") -> Frank
B11: 1001 | C11: =IFERROR(VLOOKUP(B11,'Master Emp List'!$A$2:$I$38,3,FALSE),"No EMP ID Found") -> No EMP ID Found
B12: 1002 | C12: =IFERROR(VLOOKUP(B12,'Master Emp List'!$A$2:$I$38,3,FALSE),"No EMP ID Found") -> No EMP ID Found
B13: 1003 | C13: =IFERROR(VLOOKUP(B13,'Master Emp List'!$A$2:$I$38,3,FALSE),"No EMP ID Found") -> No EMP ID Found
B14: 1302 | C14: =IFERROR(VLOOKUP(B14,'Master Emp List'!$A$2:$I$38,3,FALSE),"No EMP ID Found") -> Randy
... B18: 1368 | C18: =IFERROR(VLOOKUP(B18,'Master Emp List'!$A$2:$I$38,3,FALSE),"No EMP ID Found") -> Tammy

Sheet Master Emp List
A1: Emp ID | B1: Last Name | C1: First Name | D1: Dept | E1: E-mail | F1: Phone Ext | G1: Location | H1: Hire Date | I1: Pay Rate
A2: 1054 | B2: Smith | C2: Howard | D2: AT | E2: howards | F2: 148 | G2: Building 1 | H2: 33344 | I2: 11.25
A3: 1056 | B3: Gonzales | C3: Joe | D3: AT | E3: joeg | F3: 121 | G3: Building 1 | H3: 29153 | I3: 12.25
A4: 1067 | B4: Scote | C4: Gail | D4: AT | E4: gails | F4: 123 | G4: Building 1 | H4: 32040 | I4: 14.55
A5: 1075 | B5: Kane | C5: Sheryl | D5: AD | E5: sherylk | F5: 126 | G5: Building 2 | H5: 33823 | I5: 11.25
A6: 1078 | B6: Hapsbuch | C6: Kendrick | D6: AC | E6: kendrickh | F6: 101 | G6: Building 2 | H6: 31503 | I6: 10.2
A7: 1152 | B7: Henders | C7: Mark | D7: AD | E7: markh | F7: 118 | G7: Building 2 | H7: 32894 | I7: 12.25
A8: 1196 | B8: Atherton | C8: Katie | D8: HR | E8: katiea | F8: 289 | G8: Building 3 | H8: 35886 | I8: 9.95
A9: 1284 | B9: Bellwood | C9: Frank | D9: MK | E9: frankb | F9: 124 | G9: Building 1 | H9: 31051 | I9: 12.3
A10: 1290 | B10: Cooper | C10: Linda | D10: AD | E10: lindac | F10: 113 | G10: Building 2 | H10: 31050 | I10: 13.25
A11: 1293 | B11: Cronwith | C11: Brent | D11: HR | E11: brentc | F11: 205 | G11: Building 3 | H11: 30939 | I11: 10.2
A12: 1299 | B12: Simpson | C12: Sandrae | D12: MF | E12: sandraes | F12: 127 | G12: Building 1 | H12: 32863 | I12: 12.2
A13: 1302 | B13: Sindole | C13: Randy | D13: MK | E13: randys | F13: 139 | G13: Building 1 | H13: 30900 | I13: 14.25
... A38: 1999 | B38: Atherly | C38: Katherine | D38: HR | E38: kathya | F38: 428 | G38: Building 3 | H38: 35981 | I38: 10.15

Sheet HLOOKUP Function
A2: Inventory Status Check
A3: Enter Product Code Here: | B3: XP200
A5: Warehouse 1 Inventory: | B5: =HLOOKUP(B3,'Master Inventory List'!B2:G5,2,FALSE) -> 150
A6: Warehouse 2 Inventory:
A7: Warehouse 3 Inventory:

Sheet Master Inventory List
A2: Product Code: | B2: XP100 | C2: XP200 | D2: XP300 | E2: AX10 | F2: AX25 | G2: AX50
A3: Warehouse 1 | B3: 120 | C3: 150 | D3: 135 | E3: 90 | F3: 95 | G3: 140
A4: Warehouse 2 | B4: 55 | C4: 110 | D4: 75 | E4: 95 | F4: 75 | G4: 55
A5: Warehouse 3 | B5: 70 | C5: 115 | D5: 65 | E5: 55 | F5: 85 | G5: 65

Sheet INDEX MATCH Functions
C2: RETURNS VALUE AT A SPECIFIC POSITION | D2: RETURNS NUMERIC POSITION OF A VALUE | F2: INDEX & MATCH
B3: EMP ID | C3: INDEX | D3: MATCH | F3: LAST NAME
B4: 1054
B5: 1078
B6: 1284
B7: 1299
B8: 1329
B9: 1509

Sheet INDEX MATCH Master Emp List
A1: Emp ID | B1: Last Name | C1: First Name | D1: Dept | E1: E-mail | F1: Phone Ext | G1: Location | H1: Hire Date | I1: Pay Rate
A2: 1054 | B2: Smith | C2: Howard | D2: AT | E2: howards | F2: 148 | G2: Building 1 | H2: 33344 | I2: 11.25
A3: 1056 | B3: Gonzales | C3: Joe | D3: AT | E3: joeg | F3: 121 | G3: Building 1 | H3: 29153 | I3: 12.25
A4: 1067 | B4: Scote | C4: Gail | D4: AT | E4: gails | F4: 123 | G4: Building 1 | H4: 32040 | I4: 14.55
A5: 1075 | B5: Kane | C5: Sheryl | D5: AD | E5: sherylk | F5: 126 | G5: Building 2 | H5: 33823 | I5: 11.25
A6: 1078 | B6: Hapsbuch | C6: Kendrick | D6: AC | E6: kendrickh | F6: 101 | G6: Building 2 | H6: 31503 | I6: 10.2
A7: 1152 | B7: Henders | C7: Mark | D7: AD | E7: markh | F7: 118 | G7: Building 2 | H7: 32894 | I7: 12.25
A8: 1196 | B8: Atherton | C8: Katie | D8: HR | E8: katiea | F8: 289 | G8: Building 3 | H8: 35886 | I8: 9.95
A9: 1284 | B9: Bellwood | C9: Frank | D9: MK | E9: frankb | F9: 124 | G9: Building 1 | H9: 31051 | I9: 12.3
A10: 1290 | B10: Cooper | C10: Linda | D10: AD | E10: lindac | F10: 113 | G10: Building 2 | H10: 31050 | I10: 13.25
A11: 1293 | B11: Cronwith | C11: Brent | D11: HR | E11: brentc | F11: 205 | G11: Building 3 | H11: 30939 | I11: 10.2
A12: 1299 | B12: Simpson | C12: Sandrae | D12: MF | E12: sandraes | F12: 127 | G12: Building 1 | H12: 32863 | I12: 12.2
A13: 1302 | B13: Sindole | C13: Randy | D13: MK | E13: randys | F13: 139 | G13: Building 1 | H13: 30900 | I13: 14.25
... A38: 1999 | B38: Atherly | C38: Katherine | D38: HR | E38: kathya | F38: 428 | G38: Building 3 | H38: 35981 | I38: 10.15

Sheet LEFT RIGHT MID Functions
A2: SKU Number | B2: Product Name | C2: Retail Price | E2: Supplier ID | F2: Part # | G2: Product Code | H2: Num Chars
A3: ACM110WW | B3: Windshield Wipers #110 | C3: 13.65 | E3: =LEFT(A3,3) -> ACM | F3: =MID(A3,4,3) -> 110 | G3: =IF(LEN(A3)=10,RIGHT(A3,4),IF(LEN(A3)=9,RIGHT(A3,3),IF(LEN(A3)=8,RIGHT(A3,2),"Invalid SKU Number"))) -> WW
A4: ACM111WW | B4: Windshield Wipers #111 | C4: 12.19 | E4: =LEFT(A4,3) -> ACM | F4: =MID(A4,4,3) -> 111 | G4: =IF(LEN(A4)=10,RIGHT(A4,4),IF(LEN(A4)=9,RIGHT(A4,3),IF(LEN(A4)=8,RIGHT(A4,2),"Invalid SKU Number"))) -> WW
A5: ACM150WW | B5: Windshield Wipers #150 | C5: 10.89 | E5: =LEFT(A5,3) -> ACM | F5: =MID(A5,4,3) -> 150 | G5: =IF(LEN(A5)=10,RIGHT(A5,4),IF(LEN(A5)=9,RIGHT(A5,3),IF(LEN(A5)=8,RIGHT(A5,2),"Invalid SKU Number"))) -> WW
A6: ACM321DP | B6: Drain Plug #321 | C6: 9.75 | E6: =LEFT(A6,3) -> ACM | F6: =MID(A6,4,3) -> 321 | G6: =IF(LEN(A6)=10,RIGHT(A6,4),IF(LEN(A6)=9,RIGHT(A6,3),IF(LEN(A6)=8,RIGHT(A6,2),"Invalid SKU Number"))) -> DP
A7: ACM322DP | B7: Drain Plug #322 | C7: 9.59 | E7: =LEFT(A7,3) -> ACM | F7: =MID(A7,4,3) -> 322 | G7: =IF(LEN(A7)=10,RIGHT(A7,4),IF(LEN(A7)=9,RIGHT(A7,3),IF(LEN(A7)=8,RIGHT(A7,2),"Invalid SKU Number"))) -> DP
A8: ACM325DP | B8: Drain Plug #325 | C8: 10.4 | E8: =LEFT(A8,3) -> ACM | F8: =MID(A8,4,3) -> 325 | G8: =IF(LEN(A8)=10,RIGHT(A8,4),IF(LEN(A8)=9,RIGHT(A8,3),IF(LEN(A8)=8,RIGHT(A8,2),"Invalid SKU Number"))) -> DP
A9: ACM330DP | B9: Drain Plug #330 | C9: 10.56 | E9: =LEFT(A9,3) -> ACM | F9: =MID(A9,4,3) -> 330 | G9: =IF(LEN(A9)=10,RIGHT(A9,4),IF(LEN(A9)=9,RIGHT(A9,3),IF(LEN(A9)=8,RIGHT(A9,2),"Invalid SKU Number"))) -> DP
A10: ACM450DP | B10: Drain Plug #450 | C10: 9.75 | E10: =LEFT(A10,3) -> ACM | F10: =MID(A10,4,3) -> 450 | G10: =IF(LEN(A10)=10,RIGHT(A10,4),IF(LEN(A10)=9,RIGHT(A10,3),IF(LEN(A10)=8,RIGHT(A10,2),"Invalid SKU Number"))) -> DP
A11: ACM460DP | B11: Drain Plug #460 | C11: 9.75 | E11: =LEFT(A11,3) -> ACM | F11: =MID(A11,4,3) -> 460 | G11: =IF(LEN(A11)=10,RIGHT(A11,4),IF(LEN(A11)=9,RIGHT(A11,3),IF(LEN(A11)=8,RIGHT(A11,2),"Invalid SKU Number"))) -> DP
A12: AST530OL | B12: 5W30 | C12: 4.06 | E12: =LEFT(A12,3) -> AST | F12: =MID(A12,4,3) -> 530 | G12: =IF(LEN(A12)=10,RIGHT(A12,4),IF(LEN(A12)=9,RIGHT(A12,3),IF(LEN(A12)=8,RIGHT(A12,2),"Invalid SKU Number"))) -> OL
A13: AST100TF | B13: Automatic Transmission Fluid | C13: 5.04 | E13: =LEFT(A13,3) -> AST | F13: =MID(A13,4,3) -> 100 | G13: =IF(LEN(A13)=10,RIGHT(A13,4),IF(LEN(A13)=9,RIGHT(A13,3),IF(LEN(A13)=8,RIGHT(A13,2),"Invalid SKU Number"))) -> TF
A14: AST130OL | B14: 10W30 | C14: 3.9 | E14: =LEFT(A14,3) -> AST | F14: =MID(A14,4,3) -> 130 | G14: =IF(LEN(A14)=10,RIGHT(A14,4),IF(LEN(A14)=9,RIGHT(A14,3),IF(LEN(A14)=8,RIGHT(A14,2),"Invalid SKU Number"))) -> OL
... A26: TRA610OF | B26: Oil Filter #610 | C26: 6.14 | E26: =LEFT(A26,3) -> TRA | F26: =MID(A26,4,3) -> 610 | G26: =IF(LEN(A26)=10,RIGHT(A26,4),IF(LEN(A26)=9,RIGHT(A26,3),IF(LEN(A26)=8,RIGHT(A26,2),"Invalid SKU Number"))) -> OF

Sheet SEARCH Function
A1: Name | B1: First Name | C1: Last Name | E1: SEARCH
A2: Patrick Marleau | B2: =LEFT(A2,SEARCH(" ",A2)-1) -> Patrick | C2: =RIGHT(A2,LEN(A2)-SEARCH(" ",A2)) -> Marleau | E2: =SEARCH(" ", A2) -> 8
A3: Joe Thornton | B3: =LEFT(A3,SEARCH(" ",A3)-1) -> Joe | C3: =RIGHT(A3,LEN(A3)-SEARCH(" ",A3)) -> Thornton | E3: =SEARCH(" ", A3) -> 4
A4: Brent Burns | B4: =LEFT(A4,SEARCH(" ",A4)-1) -> Brent | C4: =RIGHT(A4,LEN(A4)-SEARCH(" ",A4)) -> Burns | E4: =SEARCH(" ", A4) -> 6
A5: Joe Pavelski | B5: =LEFT(A5,SEARCH(" ",A5)-1) -> Joe | C5: =RIGHT(A5,LEN(A5)-SEARCH(" ",A5)) -> Pavelski | E5: =SEARCH(" ", A5) -> 4
A6: Martin Jones | B6: =LEFT(A6,SEARCH(" ",A6)-1) -> Martin | C6: =RIGHT(A6,LEN(A6)-SEARCH(" ",A6)) -> Jones | E6: =SEARCH(" ", A6) -> 7

Sheet CONCAT
B2: Last Name | C2: First Name | E2: Full Name: | H2: USING &
B3: Smith | C3: Howard | E3: =_xlfn.CONCAT(C3," ",B3) -> Howard Smith | H3: =C3 & " " &B3 -> Howard Smith
B4: Gonzales | C4: Joe | E4: =_xlfn.CONCAT(C4," ",B4) -> Joe Gonzales | H4: =C4 & " " &B4 -> Joe Gonzales
B5: Scote | C5: Gail | E5: =_xlfn.CONCAT(C5," ",B5) -> Gail Scote | H5: =C5 & " " &B5 -> Gail Scote
B6: Kane | C6: Sheryl | E6: =_xlfn.CONCAT(C6," ",B6) -> Sheryl Kane | H6: =C6 & " " &B6 -> Sheryl Kane
B7: Hapsbuch | C7: Kendrick | E7: =_xlfn.CONCAT(C7," ",B7) -> Kendrick Hapsbuch | H7: =C7 & " " &B7 -> Kendrick Hapsbuch
B8: Henders | C8: Mark | E8: =_xlfn.CONCAT(C8," ",B8) -> Mark Henders | H8: =C8 & " " &B8 -> Mark Henders
B9: Atherton | C9: Katie | E9: =_xlfn.CONCAT(C9," ",B9) -> Katie Atherton | H9: =C9 & " " &B9 -> Katie Atherton
B10: Bellwood | C10: Frank | E10: =_xlfn.CONCAT(C10," ",B10) -> Frank Bellwood | H10: =C10 & " " &B10 -> Frank Bellwood
B11: Cooper | C11: Linda | E11: =_xlfn.CONCAT(C11," ",B11) -> Linda Cooper | H11: =C11 & " " &B11 -> Linda Cooper
B12: Cronwith | C12: Brent | E12: =_xlfn.CONCAT(C12," ",B12) -> Brent Cronwith | H12: =C12 & " " &B12 -> Brent Cronwith
B13: Simpson | C13: Sandrae | E13: =_xlfn.CONCAT(C13," ",B13) -> Sandrae Simpson | H13: =C13 & " " &B13 -> Sandrae Simpson
B14: Sindole | C14: Randy | E14: =_xlfn.CONCAT(C14," ",B14) -> Randy Sindole | H14: =C14 & " " &B14 -> Randy Sindole
... B18: Wu | C18: Tammy | E18: =_xlfn.CONCAT(C18," ",B18) -> Tammy Wu | H18: =C18 & " " &B18 -> Tammy Wu

Sheet Contact List
A1: Customer Name | B1: Company Name | C1: City | D1: State
A2: John Smith | B2: Acme Industries | C2: New York | D2: NY
A3: Mary-Ann O'Connor | B3: Global Solutions | C3: Los Angeles | D3: CA
A4: Kevin Brown | B4: Northwind Traders | C4: Chicago | D4: IL
A5: Sara Mcdonald | B5: Blue Sky Consulting | C5: Seattle | D5: WA
A6: Robert O’Neill | B6: Apex Logistics | C6: Dallas | D6: TX
A7: Emily Johnson | B7: Sunrise Healthcare | C7: Boston | D7: MA
A8: Michael Lee | B8: Pacific Holdings | C8: San Francisco | D8: CA
A9: Laura Garcia | B9: Horizon Retail | C9: Miami | D9: FL
A10: Daniel Thompson | B10: Silverline Finance | C10: Denver | D10: CO
A11: Jessica Martinez | B11: Evergreen Marketing | C11: Portland | D11: OR

Sheet Formula Auditing
A2: Sales Figures - December 2026 | H2: Monthly Goal: | I2: 34000
A4: Sales Person | B4: Week 1 | C4: Week 2 | D4: Week 3 | E4: Week 4 | F4: Totals | H4: Was Goal Met? | I4: Bonus Status
A5: H. James | B5: 9550 | C5: 9230 | D5: 8500 | E5: 8965 | F5: =SUM(B5:E5) -> 36245 | H5: =IF(F5>=I2,"YES", "NO") -> YES | I5: =IF(AND(H5="YES ", MIN(B5:E5)>=8000), "BONUS", "NO BONUS") -> NO BONUS
A6: K. Dunn | B6: 5975 | C6: 6900 | D6: 8500 | E6: 10100 | F6: =SUM(B6:E6) -> 31475 | H6: =IF(F6>=I3,"YES", "NO") -> YES | I6: =IF(AND(H6="YES", MIN(B6:E6)>=8000), "BONUS", "NO BONUS") -> NO BONUS
A7: L. Carrie | B7: 7425 | C7: 8580 | D7: 9910 | E7: 7512 | F7: =SUM(B7:E7) -> 33427 | H7: =IF(F7>=I4,"YES", "NO") -> NO | I7: =IF(AND(H7="YES", MIN(B7:E7)>=8000), "BONUS", "NO BONUS") -> NO BONUS
A8: R. Smith | B8: 9560 | C8: 10150 | D8: 10200 | E8: 9795 | F8: =SUM(B8:E8) -> 39705 | H8: =IF(F8>=I5,"YES ", "NO") -> NO | I8: =IF(AND(H8="YES", MIN(B8:E8)>=8000), "BONUS", "NO BONUS") -> NO BONUS
A9: D. O'Brian | B9: 7892 | C9: 7695 | D9: 9520 | E9: 10252 | F9: =SUM(B9:E9) -> 35359 | H9: =IF(F9>=I6,"YES", "NO") -> NO | I9: =IF(AND(H9="YES", MIN(B9:E9)>=8000), "BONUS", "NO BONUS") -> NO BONUS
A10: Weekly Total | B10: =SUM(B5:B9) -> 40402 | C10: =SUM(C5:C9) -> 42555 | D10: =SUM(D5:D9) -> 46630 | E10: =SUM(E5:E9) -> 46624 | F10: =SUM(F5:F8) -> 140852
A12: Current number of sales people who haved reached their goal: | F12: =COUNTIF(H5:H9, "YES") -> 2

Sheet Transactions
A1: Order Date | B1: Sales Rep | C1: Region | D1: Product | E1: Units Sold | F1: Revenue
A2: 45658 | B2: Abigail Miller | C2: South | D2: Dell Latitude 5540 | E2: 9 | F2: 7715
A3: 45658 | B3: James Wilson | C3: West | D3: Samsung Galaxy S24 | E3: 11 | F3: 8584
A4: 45659 | B4: Henry Moore | C4: South | D4: iPhone 15 | E4: 9 | F4: 11386
A5: 45659 | B5: Olivia Hernandez | C5: South | D5: Lenovo ThinkPad E16 | E5: 12 | F5: 3848
A6: 45661 | B6: Olivia Hernandez | C6: West | D6: Lenovo ThinkPad E16 | E6: 9 | F6: 6793
A7: 45661 | B7: Sophia Martin | C7: South | D7: HP ProBook 450 | E7: 1 | F7: 3873
A8: 45661 | B8: Lucas Lopez | C8: Central | D8: Lenovo ThinkPad E16 | E8: 2 | F8: 5999
A9: 45662 | B9: Emma Thomas | C9: West | D9: Lenovo ThinkPad E16 | E9: 5 | F9: 2713
A10: 45662 | B10: Mia Garcia | C10: West | D10: Lenovo ThinkPad E16 | E10: 12 | F10: 11870
A11: 45663 | B11: Lucas Lopez | C11: Central | D11: Lenovo ThinkPad E16 | E11: 7 | F11: 3464
A12: 45663 | B12: Sophia Martin | C12: West | D12: Samsung Galaxy S24 | E12: 3 | F12: 4509
A13: 45663 | B13: Harper Martinez | C13: West | D13: iPhone 15 | E13: 11 | F13: 3761
... A851: 46022 | B851: Harper Martinez | C851: East | D851: Microsoft Surface Laptop 6 | E851: 4 | F851: 6229

Sheet Transaction Summary
B2: Metric | C2: Value
B3: Total Revenue | C3: =SUM(tblTransactions[Revenue]) -> 5305462
B4: Average Deal Size | C4: =AVERAGE(tblTransactions[Revenue]) -> 6241.72
B5: Top Sales Rep (by Revenue) | C5: =INDEX(tblTransactions[Sales Rep],MATCH(MAX(tblTransactions[Revenue]),tblTransactions[Revenue],0)) -> James Wilson
B6: West Region Revenue | C6: =SUMIF(tblTransactions[Region],"West",tblTransactions[Revenue]) -> 1524883
B7: East Region Revenue | C7: =SUMIF(tblTransactions[Region],"East",tblTransactions[Revenue]) -> 1723481

Sheet Worksheet Protection
A2: Sales Figures - December 2026 | H2: Monthly Goal: | I2: 34000
A4: Sales Person | B4: Week 1 | C4: Week 2 | D4: Week 3 | E4: Week 4 | F4: Totals | H4: Was Goal Met? | I4: Bonus Status
A5: H. James | B5: 9550 | C5: 9230 | D5: 8500 | E5: 8965 | F5: =SUM(B5:E5) -> 36245 | H5: =IF(F5>=$I$2,"YES", "NO") -> YES | I5: =IF(AND(H5="YES", MIN(B5:E5)>=8000), "BONUS", "NO BONUS") -> BONUS
A6: K. Dunn | B6: 5975 | C6: 6900 | D6: 8500 | E6: 10100 | F6: =SUM(B6:E6) -> 31475 | H6: =IF(F6>=$I$2,"YES", "NO") -> NO | I6: =IF(AND(H6="YES", MIN(B6:E6)>=8000), "BONUS", "NO BONUS") -> NO BONUS
A7: L. Carrie | B7: 7425 | C7: 8580 | D7: 9910 | E7: 7512 | F7: =SUM(B7:E7) -> 33427 | H7: =IF(F7>=$I$2,"YES", "NO") -> NO | I7: =IF(AND(H7="YES", MIN(B7:E7)>=8000), "BONUS", "NO BONUS") -> NO BONUS
A8: R. Smith | B8: 9560 | C8: 10150 | D8: 10200 | E8: 9795 | F8: =SUM(B8:E8) -> 39705 | H8: =IF(F8>=$I$2,"YES", "NO") -> YES | I8: =IF(AND(H8="YES", MIN(B8:E8)>=8000), "BONUS", "NO BONUS") -> BONUS
A9: D. O'Brian | B9: 7892 | C9: 7695 | D9: 9520 | E9: 10252 | F9: =SUM(B9:E9) -> 35359 | H9: =IF(F9>=$I$2,"YES", "NO") -> YES | I9: =IF(AND(H9="YES", MIN(B9:E9)>=8000), "BONUS", "NO BONUS") -> NO BONUS
A10: Weekly Total | B10: =SUM(B5:B9) -> 40402 | C10: =SUM(C5:C9) -> 42555 | D10: =SUM(D5:D9) -> 46630 | E10: =SUM(E5:E9) -> 46624 | F10: =SUM(F5:F9) -> 176211
A12: Current number of sales people who haved reached their goal: | F12: =COUNTIF(H5:H9, "YES") -> 3

Sheet Goal Seek
A2: Mortgage Amount: | B2: 220000 | D2: Current PMT
A3: Interest Rate: | B3: 0.08
A4: Term in Months: | B4: 300

Sheet Solver
G3: Shipping | H3: Total Cost of
B4: 1QTR | C4: 2QTR | D4: 3QTR | E4: 4QTR | G4: Per Unit | H4: Shipping
A5: Plant 1: | B5: 1 | C5: 1 | D5: 1 | E5: 1 | G5: 1.25 | H5: =G5*(B5+C5+D5+E5) -> 5
A6: Plant 2: | B6: 0 | C6: 0 | D6: 0 | E6: 0 | G6: 1.84 | H6: =G6*(B6+C6+D6+E6) -> 0
A7: Plant 3: | B7: 0 | C7: 0 | D7: 0 | E7: 0 | G7: 1.45 | H7: =G7*(B7+C7+D7+E7) -> 0
A8: Total Units Produced: | B8: =SUM(B5:B7) -> 1 | C8: =SUM(C5:C7) -> 1 | D8: =SUM(D5:D7) -> 1 | E8: =SUM(E5:E7) -> 1 | H8: =H5+H6+H7 -> 5
A10: Warehouse Demands: | B10: 180 | C10: 80 | D10: 190 | E10: 160

Sheet Data Table
B2: Mortgage Amount: | C2: 220000
B3: Interest Rate: | C3: 0.08
B4: Term in Months: | C4: =25*12 -> 300
B7: % Rate | C7: =-PMT(C3/12,C4,C2) -> 1697.9957
B8: 0.0725
B9: 0.075
B10: 0.0775
B11: 0.0825
B12: 0.085
B13: 0.0875
B14: 0.09

Sheet Scenarios
B2: Region | C2: Q1 | D2: Q2 | E2: Q3 | F2: Q4 | G2: Yearly Total
B3: North | C3: 85292.25 | D3: =C3*C11+C3 -> 88106.894 | E3: =D3*C11+D3 -> 91014.422 | F3: =E3*C11+E3 -> 94017.898 | G3: =SUM(C3:F3) -> 358431.46
B4: East | C4: 75891.25 | D4: =C4*C12+C4 -> 77636.749 | E4: =D4*C12+D4 -> 79422.394 | F4: =E4*C12+E4 -> 81249.109 | G4: =SUM(C4:F4) -> 314199.5
B5: West | C5: 90568.34 | D5: =C5*C13+C5 -> 94462.779 | E5: =D5*C13+D5 -> 98524.678 | F5: =E5*C13+E5 -> 102761.24 | G5: =SUM(C5:F5) -> 386317.04
B6: South | C6: 65897.25 | D6: =C6*C14+C6 -> 66622.12 | E6: =D6*C14+D6 -> 67354.963 | F6: =E6*C14+E6 -> 68095.868 | G6: =SUM(C6:F6) -> 267970.2
B7: Totals: | C7: =SUM(C3:C6) -> 317649.09 | D7: =SUM(D3:D6) -> 326828.54 | E7: =SUM(E3:E6) -> 336316.46 | F7: =SUM(F3:F6) -> 346124.11 | G7: =SUM(G3:G6) -> 1326918.2
B10: Predicted Sales Growth
B11: North | C11: 0.033
B12: East | C12: 0.023
B13: West | C13: 0.043
B14: South | C14: 0.011

Sheet Macro
A1: 1054 | B1: Smith | C1: Howard | D1: AT | E1: howards | F1: 148 | G1: Building 1 | H1: 33344 | I1: 11.25
A2: 1056 | B2: Gonzales | C2: Joe | D2: AT | E2: joeg | F2: 121 | G2: Building 1 | H2: 29153 | I2: 12.25
A3: 1067 | B3: Scote | C3: Gail | D3: AT | E3: gails | F3: 123 | G3: Building 1 | H3: 32040 | I3: 14.55
A4: 1075 | B4: Kane | C4: Sheryl | D4: AD | E4: sherylk | F4: 126 | G4: Building 2 | H4: 33823 | I4: 11.25
A5: 1078 | B5: Hapsbuch | C5: Kendrick | D5: AC | E5: kendrickh | F5: 101 | G5: Building 2 | H5: 31503 | I5: 10.2
A6: 1152 | B6: Henders | C6: Mark | D6: AD | E6: markh | F6: 118 | G6: Building 2 | H6: 32894 | I6: 12.25
A7: 1196 | B7: Atherton | C7: Katie | D7: HR | E7: katiea | F7: 289 | G7: Building 3 | H7: 35886 | I7: 9.95
A8: 1284 | B8: Bellwood | C8: Frank | D8: MK | E8: frankb | F8: 124 | G8: Building 1 | H8: 31051 | I8: 12.3
A9: 1290 | B9: Cooper | C9: Linda | D9: AD | E9: lindac | F9: 113 | G9: Building 2 | H9: 31050 | I9: 13.25
A10: 1293 | B10: Cronwith | C10: Brent | D10: HR | E10: brentc | F10: 205 | G10: Building 3 | H10: 30939 | I10: 10.2
A11: 1299 | B11: Simpson | C11: Sandrae | D11: MF | E11: sandraes | F11: 127 | G11: Building 1 | H11: 32863 | I11: 12.2
A12: 1302 | B12: Sindole | C12: Randy | D12: MK | E12: randys | F12: 139 | G12: Building 1 | H12: 30900 | I12: 14.25
... A23: 1676 | B23: Miller | C23: Janet | D23: MK | E23: janetm | F23: 115 | G23: Building 1 | H23: 29885 | I23: 10.75

Sheet Test Macro
A1: 1054 | B1: Smith | C1: Howard | D1: AT | E1: howards | F1: 148 | G1: Building 1 | H1: 33344 | I1: 11.25
A2: 1056 | B2: Gonzales | C2: Joe | D2: AT | E2: joeg | F2: 121 | G2: Building 1 | H2: 29153 | I2: 12.25
A3: 1067 | B3: Scote | C3: Gail | D3: AT | E3: gails | F3: 123 | G3: Building 1 | H3: 32040 | I3: 14.55
A4: 1075 | B4: Kane | C4: Sheryl | D4: AD | E4: sherylk | F4: 126 | G4: Building 2 | H4: 33823 | I4: 11.25
A5: 1078 | B5: Hapsbuch | C5: Kendrick | D5: AC | E5: kendrickh | F5: 101 | G5: Building 2 | H5: 31503 | I5: 10.2
A6: 1152 | B6: Henders | C6: Mark | D6: AD | E6: markh | F6: 118 | G6: Building 2 | H6: 32894 | I6: 12.25
A7: 1196 | B7: Atherton | C7: Katie | D7: HR | E7: katiea | F7: 289 | G7: Building 3 | H7: 35886 | I7: 9.95
A8: 1284 | B8: Bellwood | C8: Frank | D8: MK | E8: frankb | F8: 124 | G8: Building 1 | H8: 31051 | I8: 12.3
A9: 1290 | B9: Cooper | C9: Linda | D9: AD | E9: lindac | F9: 113 | G9: Building 2 | H9: 31050 | I9: 13.25
A10: 1293 | B10: Cronwith | C10: Brent | D10: HR | E10: brentc | F10: 205 | G10: Building 3 | H10: 30939 | I10: 10.2
A11: 1299 | B11: Simpson | C11: Sandrae | D11: MF | E11: sandraes | F11: 127 | G11: Building 1 | H11: 32863 | I11: 12.2
A12: 1302 | B12: Sindole | C12: Randy | D12: MK | E12: randys | F12: 139 | G12: Building 1 | H12: 30900 | I12: 14.25
... A37: 1999 | B37: Atherly | C37: Katherine | D37: HR | E37: kathya | F37: 428 | G37: Building 3 | H37: 35981 | I37: 10.15

Sheet Test Edited Macro
A1: 1054 | B1: Smith | C1: Howard | D1: AT | E1: howards | F1: 148 | G1: Building 1 | H1: 33344 | I1: 11.25
A2: 1056 | B2: Gonzales | C2: Joe | D2: AT | E2: joeg | F2: 121 | G2: Building 1 | H2: 29153 | I2: 12.25
A3: 1067 | B3: Scote | C3: Gail | D3: AT | E3: gails | F3: 123 | G3: Building 1 | H3: 32040 | I3: 14.55
A4: 1075 | B4: Kane | C4: Sheryl | D4: AD | E4: sherylk | F4: 126 | G4: Building 2 | H4: 33823 | I4: 11.25
A5: 1078 | B5: Hapsbuch | C5: Kendrick | D5: AC | E5: kendrickh | F5: 101 | G5: Building 2 | H5: 31503 | I5: 10.2
A6: 1152 | B6: Henders | C6: Mark | D6: AD | E6: markh | F6: 118 | G6: Building 2 | H6: 32894 | I6: 12.25
A7: 1196 | B7: Atherton | C7: Katie | D7: HR | E7: katiea | F7: 289 | G7: Building 3 | H7: 35886 | I7: 9.95
A8: 1284 | B8: Bellwood | C8: Frank | D8: MK | E8: frankb | F8: 124 | G8: Building 1 | H8: 31051 | I8: 12.3
A9: 1290 | B9: Cooper | C9: Linda | D9: AD | E9: lindac | F9: 113 | G9: Building 2 | H9: 31050 | I9: 13.25
A10: 1293 | B10: Cronwith | C10: Brent | D10: HR | E10: brentc | F10: 205 | G10: Building 3 | H10: 30939 | I10: 10.2
A11: 1299 | B11: Simpson | C11: Sandrae | D11: MF | E11: sandraes | F11: 127 | G11: Building 1 | H11: 32863 | I11: 12.2
A12: 1302 | B12: Sindole | C12: Randy | D12: MK | E12: randys | F12: 139 | G12: Building 1 | H12: 30900 | I12: 14.25
... A37: 1999 | B37: Atherly | C37: Katherine | D37: HR | E37: kathya | F37: 428 | G37: Building 3 | H37: 35981 | I37: 10.15
